juntagrico_assignment_request/__init__.py
juntagrico_assignment_request/admin.py
juntagrico_assignment_request/apps.py
juntagrico_assignment_request/forms.py
juntagrico_assignment_request/hack.py
juntagrico_assignment_request/models.py
juntagrico_assignment_request/urls.py
juntagrico_assignment_request/utils.py
juntagrico_assignment_request/view_decorators.py
juntagrico_assignment_request/views.py
juntagrico_assignment_request/admins/__init__.py
juntagrico_assignment_request/admins/assignment_request_admin.py
juntagrico_assignment_request/mailer/__init__.py
juntagrico_assignment_request/mailer/adminnotification.py
juntagrico_assignment_request/mailer/membernotification.py
juntagrico_assignment_request/migrations/0001_squashed_0006_auto_20191020_2203.py
juntagrico_assignment_request/migrations/0002_fix_naming_and_relation.py
juntagrico_assignment_request/migrations/0003_change_assignment_helptext.py
juntagrico_assignment_request/migrations/0004_auto_20211207_1101.py
juntagrico_assignment_request/migrations/0005_alter_assignmentrequest_amount.py
juntagrico_assignment_request/migrations/0006_alter_assignmentrequest_options.py
juntagrico_assignment_request/migrations/__init__.py
juntagrico_assignment_request/static/juntagrico_assignment_request/js/request.js
juntagrico_assignment_request/templates/assignment_request/edit.html
juntagrico_assignment_request/templates/assignment_request/list.html
juntagrico_assignment_request/templates/assignment_request/request.html
juntagrico_assignment_request/templates/assignment_request/respond.html
juntagrico_assignment_request/templates/assignment_request/mails/admin/edited.txt
juntagrico_assignment_request/templates/assignment_request/mails/admin/new.txt
juntagrico_assignment_request/templates/assignment_request/mails/admin/notify_original_approver.txt
juntagrico_assignment_request/templates/assignment_request/mails/member/confirmed.txt
juntagrico_assignment_request/templates/assignment_request/mails/member/rejected.txt
juntagrico_assignment_request-1.7.0.dist-info/licenses/LICENSE
juntagrico_assignment_request-1.7.0.dist-info/METADATA
juntagrico_assignment_request-1.7.0.dist-info/WHEEL
juntagrico_assignment_request-1.7.0.dist-info/top_level.txt
juntagrico_assignment_request-1.7.0.dist-info/RECORD
